ddq_tkinter/__init__.py
ddq_tkinter/ddq_config_manager/__init__.py
ddq_tkinter/ddq_config_manager/config_manager.py
ddq_tkinter/ddq_config_manager/config_panel.py
ddq_tkinter/ddq_config_manager/configurable_tool.py
ddq_tkinter/ddq_widgets/__init__.py
ddq_tkinter/ddq_widgets/ddq_button.py
ddq_tkinter/ddq_widgets/ddq_button_group.py
ddq_tkinter/ddq_widgets/ddq_card.py
ddq_tkinter/ddq_widgets/ddq_checkbox.py
ddq_tkinter/ddq_widgets/ddq_file_picker.py
ddq_tkinter/ddq_widgets/ddq_form.py
ddq_tkinter/ddq_widgets/ddq_form_item.py
ddq_tkinter/ddq_widgets/ddq_input.py
ddq_tkinter/ddq_widgets/ddq_listbox.py
ddq_tkinter/ddq_widgets/ddq_password_input.py
ddq_tkinter/ddq_widgets/ddq_radio.py
ddq_tkinter/ddq_widgets/ddq_scrollable.py
ddq_tkinter/ddq_widgets/ddq_select.py
ddq_tkinter/ddq_widgets/ddq_space.py
ddq_tkinter/ddq_widgets/ddq_split_layout.py
ddq_tkinter/ddq_widgets/ddq_table.py
ddq_tkinter/ddq_widgets/ddq_text.py
ddq_tkinter/ddq_widgets/ddq_textarea.py
ddq_tkinter/ddq_widgets/ddq_toast.py
ddq_tkinter/examples/__init__.py
ddq_tkinter/examples/demo.py
ddq_tkinter/examples/demo_button.py
ddq_tkinter/examples/demo_button_group.py
ddq_tkinter/examples/demo_card.py
ddq_tkinter/examples/demo_checkbox.py
ddq_tkinter/examples/demo_file_picker.py
ddq_tkinter/examples/demo_form.py
ddq_tkinter/examples/demo_form_item.py
ddq_tkinter/examples/demo_listbox.py
ddq_tkinter/examples/demo_scrollable_text.py
ddq_tkinter/examples/demo_select.py
ddq_tkinter/examples/demo_split_layout.py
ddq_tkinter/examples/demo_table.py
ddq_tkinter/examples/demo_text.py
ddq_tkinter/examples/demo_config_manager/__init__.py
ddq_tkinter/examples/demo_config_manager/configurable_tool_demo.py
ddq_tkinter/examples/demo_config_manager/run_demo.py
ddq_tkinter/tests/__init__.py
ddq_tkinter/tests/conftest.py
ddq_tkinter/tests/test_config_manager/__init__.py
ddq_tkinter/tests/test_config_manager/test_config_manager.py
ddq_tkinter/tests/test_config_manager/test_config_panel.py
ddq_ui-0.1.7.dist-info/METADATA
ddq_ui-0.1.7.dist-info/WHEEL
ddq_ui-0.1.7.dist-info/top_level.txt
ddq_ui-0.1.7.dist-info/RECORD
