Metadata-Version: 2.2
Name: ddq_ui
Version: 0.1.7
Summary: DDQ UI Framework - 一个灵活的 UI 框架，支持多种后端实现
Home-page: https://github.com/ddq/ddq_ui
Author: DDQ
Author-email: ddq@example.com
Project-URL: Documentation, https://github.com/ddq/ddq_ui#readme
Project-URL: Source, https://github.com/ddq/ddq_ui
Project-URL: Tracker, https://github.com/ddq/ddq_ui/issues
Keywords: ui,tkinter,framework,widgets
Classifier: Development Status :: 3 - Alpha
Classifier: Intended Audience :: Developers
Classifier: Programming Language :: Python :: 3
Classifier: Programming Language :: Python :: 3.6
Classifier: Programming Language :: Python :: 3.7
Classifier: Programming Language :: Python :: 3.8
Classifier: Programming Language :: Python :: 3.9
Classifier: Programming Language :: Python :: 3.10
Classifier: License :: OSI Approved :: MIT License
Classifier: Operating System :: OS Independent
Classifier: Topic :: Software Development :: Libraries :: Python Modules
Classifier: Topic :: Software Development :: User Interfaces
Requires-Python: >=3.6
Dynamic: author
Dynamic: author-email
Dynamic: classifier
Dynamic: description
Dynamic: description-content-type
Dynamic: home-page
Dynamic: keywords
Dynamic: project-url
Dynamic: requires-python
Dynamic: summary
